prom/__init__.py
prom/compat.py
prom/config.py
prom/exception.py
prom/model.py
prom/query.py
prom/utils.py
prom/extras/__init__.py
prom/extras/testdata.py
prom/interface/__init__.py
prom/interface/base.py
prom/interface/postgres.py
prom/interface/sql.py
prom/interface/sqlite.py
prom-5.4.1.dist-info/licenses/LICENSE.txt
prom-5.4.1.dist-info/METADATA
prom-5.4.1.dist-info/WHEEL
prom-5.4.1.dist-info/top_level.txt
prom-5.4.1.dist-info/RECORD
