Metadata-Version: 2.4
Name: prom
Version: 5.4.1
Summary: A sensible orm for PostgreSQL or SQLite
Author-email: Jay Marcyes <jay@marcyes.com>
License-Expression: MIT
Project-URL: Homepage, https://github.com/Jaymon/prom
Project-URL: Repository, https://github.com/Jaymon/prom
Keywords: async,postgresql,postgres,database,db,sqlite,orm
Classifier: Development Status :: 5 - Production/Stable
Classifier: Environment :: Web Environment
Classifier: Environment :: Other Environment
Classifier: Environment :: Console
Classifier: Intended Audience :: Developers
Classifier: Operating System :: OS Independent
Classifier: Topic :: Database
Classifier: Topic :: Software Development :: Libraries
Classifier: Topic :: Utilities
Classifier: Programming Language :: Python :: 3
Requires-Python: >=3.10
License-File: LICENSE.txt
Requires-Dist: dsnparse
Requires-Dist: datatypes
Provides-Extra: tests
Requires-Dist: testdata; extra == "tests"
Provides-Extra: sqlite
Requires-Dist: aiosqlite; extra == "sqlite"
Provides-Extra: postgres
Requires-Dist: psycopg; extra == "postgres"
Dynamic: license-file
